{
    "swagger": "2.0",
    "info": {
        "contact": {}
    },
    "paths": {
        "/": {
            "get": {
                "description": "handles any route and method and forwards it to the identity service as if the caller called identity directly",
                "consumes": [
                    "application/json"
                ],
                "produces": [
                    "application/json"
                ],
                "summary": "forwards requests to identity service",
                "responses": {
                    "200": {
                        "description": "OK"
                    }
                }
            },
            "post": {
                "description": "handles any route and method and forwards it to the identity service as if the caller called identity directly",
                "consumes": [
                    "application/json"
                ],
                "produces": [
                    "application/json"
                ],
                "summary": "forwards requests to identity service",
                "responses": {
                    "200": {
                        "description": "OK"
                    }
                }
            }
        }
    }
}